scocp/__init__.py
scocp/_integrator_scipy.py
scocp/_keplerder.py
scocp/_misc.py
scocp/_scvxstar.py
scocp/eoms/__init__.py
scocp/eoms/_cr3bp_scipy.py
scocp/eoms/_twobody_scipy.py
scocp/scocp_continuous/__init__.py
scocp/scocp_continuous/_ballistic.py
scocp/scocp_continuous/_rdv_fixed.py
scocp/scocp_continuous/_rdv_free.py
scocp/scocp_continuous/_rdv_free_moving.py
scocp/scocp_continuous/_scocp_continuous.py
scocp/scocp_impulsive/__init__.py
scocp/scocp_impulsive/_rdv_fixed.py
scocp/scocp_impulsive/_rdv_free_moving.py
scocp/scocp_impulsive/_scocp_impulsive.py
scocp-0.1.7.dist-info/licenses/LICENSE
scocp-0.1.7.dist-info/METADATA
scocp-0.1.7.dist-info/WHEEL
scocp-0.1.7.dist-info/top_level.txt
scocp-0.1.7.dist-info/RECORD
