Metadata-Version: 2.4
Name: scocp
Version: 0.1.7
Summary: Sequential Convex Optimization Control Problem
Home-page: https://github.com/Yuricst/scocp
Author: Yuri Shimane
Author-email: yuri.shimane@gatech.edu
License: GPL-3.0 License
Keywords: astrodynamics
Classifier: Programming Language :: Python :: 3.8
Classifier: Programming Language :: Python :: 3.9
Classifier: Programming Language :: Python :: 3.10
Classifier: Programming Language :: Python :: 3.11
Classifier: Programming Language :: Python :: 3.12
Classifier: Programming Language :: Python :: 3.13
Classifier: Programming Language :: Python :: 3.14
License-File: LICENSE
Requires-Dist: cvxpy>=1.5.3
Requires-Dist: numba>=0.54.0
Requires-Dist: numpy>=1.20.4
Requires-Dist: matplotlib>=3.8.4
Requires-Dist: scipy>=1.13.0
Dynamic: author
Dynamic: author-email
Dynamic: classifier
Dynamic: description
Dynamic: description-content-type
Dynamic: home-page
Dynamic: keywords
Dynamic: license
Dynamic: license-file
Dynamic: requires-dist
Dynamic: summary
